vibium_linux_x64/__init__.py
vibium_linux_x64/bin/clicker
vibium_linux_x64-0.1.4.dist-info/METADATA
vibium_linux_x64-0.1.4.dist-info/WHEEL
vibium_linux_x64-0.1.4.dist-info/licenses/LICENSE
vibium_linux_x64-0.1.4.dist-info/licenses/NOTICE
vibium_linux_x64-0.1.4.dist-info/RECORD
