Metadata-Version: 2.4
Name: vibium-linux-x64
Version: 0.1.4
Summary: Vibium clicker binary for Linux x64
Project-URL: Homepage, https://vibium.com
Project-URL: Repository, https://github.com/VibiumDev/vibium
Author-email: Jason Huggins <hugs@vibium.com>
License-Expression: Apache-2.0
License-File: LICENSE
License-File: NOTICE
Requires-Python: >=3.9
